odoo/addons/hr_operating_unit/README.rst
odoo/addons/hr_operating_unit/__init__.py
odoo/addons/hr_operating_unit/__manifest__.py
odoo/addons/hr_operating_unit/i18n/es.po
odoo/addons/hr_operating_unit/i18n/hr_operating_unit.pot
odoo/addons/hr_operating_unit/models/__init__.py
odoo/addons/hr_operating_unit/models/hr_employee.py
odoo/addons/hr_operating_unit/models/hr_operating_unit.py
odoo/addons/hr_operating_unit/readme/CONTRIBUTORS.rst
odoo/addons/hr_operating_unit/readme/DESCRIPTION.rst
odoo/addons/hr_operating_unit/readme/USAGE.rst
odoo/addons/hr_operating_unit/security/security.xml
odoo/addons/hr_operating_unit/static/description/icon.png
odoo/addons/hr_operating_unit/static/description/index.html
odoo/addons/hr_operating_unit/views/hr_employee.xml
odoo12_addon_hr_operating_unit-12.0.1.0.0.99.dev5.dist-info/METADATA
odoo12_addon_hr_operating_unit-12.0.1.0.0.99.dev5.dist-info/WHEEL
odoo12_addon_hr_operating_unit-12.0.1.0.0.99.dev5.dist-info/top_level.txt
odoo12_addon_hr_operating_unit-12.0.1.0.0.99.dev5.dist-info/RECORD
